{"v":5,"entries":{"components-actionitem--docs":{"id":"components-actionitem--docs","title":"Components/ActionItem","name":"Docs","importPath":"./src/components/ActionItem.stories.jsx","type":"docs","tags":["dev","test","autodocs"],"storiesImports":[]},"components-actionitem--default":{"type":"story","id":"components-actionitem--default","name":"Default","title":"Components/ActionItem","importPath":"./src/components/ActionItem.stories.jsx","componentPath":"./src/components/ActionItem.jsx","tags":["dev","test","autodocs"]},"components-actionitem--urgent":{"type":"story","id":"components-actionitem--urgent","name":"Urgent","title":"Components/ActionItem","importPath":"./src/components/ActionItem.stories.jsx","componentPath":"./src/components/ActionItem.jsx","tags":["dev","test","autodocs"]},"components-blocker--docs":{"id":"components-blocker--docs","title":"Components/Blocker","name":"Docs","importPath":"./src/components/Blocker.stories.jsx","type":"docs","tags":["dev","test","autodocs"],"storiesImports":[]},"components-blocker--default":{"type":"story","id":"components-blocker--default","name":"Default","title":"Components/Blocker","importPath":"./src/components/Blocker.stories.jsx","componentPath":"./src/components/Blocker.jsx","tags":["dev","test","autodocs"]},"components-blocker--no-reporter":{"type":"story","id":"components-blocker--no-reporter","name":"No Reporter","title":"Components/Blocker","importPath":"./src/components/Blocker.stories.jsx","componentPath":"./src/components/Blocker.jsx","tags":["dev","test","autodocs"]},"components-callout--docs":{"id":"components-callout--docs","title":"Components/Callout","name":"Docs","importPath":"./src/components/Callout.stories.jsx","type":"docs","tags":["dev","test","autodocs"],"storiesImports":[]},"components-callout--tip":{"type":"story","id":"components-callout--tip","name":"Tip","title":"Components/Callout","importPath":"./src/components/Callout.stories.jsx","componentPath":"./src/components/Callout.jsx","tags":["dev","test","autodocs"]},"components-callout--warning":{"type":"story","id":"components-callout--warning","name":"Warning","title":"Components/Callout","importPath":"./src/components/Callout.stories.jsx","componentPath":"./src/components/Callout.jsx","tags":["dev","test","autodocs"]},"components-callout--error":{"type":"story","id":"components-callout--error","name":"Error","title":"Components/Callout","importPath":"./src/components/Callout.stories.jsx","componentPath":"./src/components/Callout.jsx","tags":["dev","test","autodocs"]},"components-codesnippet--docs":{"id":"components-codesnippet--docs","title":"Components/CodeSnippet","name":"Docs","importPath":"./src/components/CodeSnippet.stories.jsx","type":"docs","tags":["dev","test","autodocs"],"storiesImports":[]},"components-codesnippet--java-script":{"type":"story","id":"components-codesnippet--java-script","name":"Java Script","title":"Components/CodeSnippet","importPath":"./src/components/CodeSnippet.stories.jsx","componentPath":"./src/components/CodeSnippet.jsx","tags":["dev","test","autodocs"]},"components-codesnippet--python":{"type":"story","id":"components-codesnippet--python","name":"Python","title":"Components/CodeSnippet","importPath":"./src/components/CodeSnippet.stories.jsx","componentPath":"./src/components/CodeSnippet.jsx","tags":["dev","test","autodocs"]},"components-iconbullet--docs":{"id":"components-iconbullet--docs","title":"Components/IconBullet","name":"Docs","importPath":"./src/components/IconBullet.stories.jsx","type":"docs","tags":["dev","test","autodocs"],"storiesImports":[]},"components-iconbullet--default":{"type":"story","id":"components-iconbullet--default","name":"Default","title":"Components/IconBullet","importPath":"./src/components/IconBullet.stories.jsx","componentPath":"./src/components/IconBullet.jsx","tags":["dev","test","autodocs"]},"components-iconbullet--task-step":{"type":"story","id":"components-iconbullet--task-step","name":"Task Step","title":"Components/IconBullet","importPath":"./src/components/IconBullet.stories.jsx","componentPath":"./src/components/IconBullet.jsx","tags":["dev","test","autodocs"]},"components-idea--docs":{"id":"components-idea--docs","title":"Components/Idea","name":"Docs","importPath":"./src/components/Idea.stories.jsx","type":"docs","tags":["dev","test","autodocs"],"storiesImports":[]},"components-idea--high-priority":{"type":"story","id":"components-idea--high-priority","name":"High Priority","title":"Components/Idea","importPath":"./src/components/Idea.stories.jsx","componentPath":"./src/components/Idea.jsx","tags":["dev","test","autodocs"]},"components-idea--medium-priority":{"type":"story","id":"components-idea--medium-priority","name":"Medium Priority","title":"Components/Idea","importPath":"./src/components/Idea.stories.jsx","componentPath":"./src/components/Idea.jsx","tags":["dev","test","autodocs"]},"components-image--docs":{"id":"components-image--docs","title":"Components/Image","name":"Docs","importPath":"./src/components/Image.stories.jsx","type":"docs","tags":["dev","test","autodocs"],"storiesImports":[]},"components-image--default":{"type":"story","id":"components-image--default","name":"Default","title":"Components/Image","importPath":"./src/components/Image.stories.jsx","componentPath":"./src/components/Image.jsx","tags":["dev","test","autodocs"]},"components-image--no-caption":{"type":"story","id":"components-image--no-caption","name":"No Caption","title":"Components/Image","importPath":"./src/components/Image.stories.jsx","componentPath":"./src/components/Image.jsx","tags":["dev","test","autodocs"]},"components-interactivetaskcard--docs":{"id":"components-interactivetaskcard--docs","title":"Components/InteractiveTaskCard","name":"Docs","importPath":"./src/components/InteractiveTaskCard.stories.jsx","type":"docs","tags":["dev","test","autodocs"],"storiesImports":[]},"components-interactivetaskcard--basic-task":{"type":"story","id":"components-interactivetaskcard--basic-task","name":"Basic Task","title":"Components/InteractiveTaskCard","importPath":"./src/components/InteractiveTaskCard.stories.jsx","componentPath":"./src/components/InteractiveTaskCard.jsx","tags":["dev","test","autodocs"]},"components-interactivetaskcard--deployment-task":{"type":"story","id":"components-interactivetaskcard--deployment-task","name":"Deployment Task","title":"Components/InteractiveTaskCard","importPath":"./src/components/InteractiveTaskCard.stories.jsx","componentPath":"./src/components/InteractiveTaskCard.jsx","tags":["dev","test","autodocs"]},"components-interactivetaskcard--bug-fix-task":{"type":"story","id":"components-interactivetaskcard--bug-fix-task","name":"Bug Fix Task","title":"Components/InteractiveTaskCard","importPath":"./src/components/InteractiveTaskCard.stories.jsx","componentPath":"./src/components/InteractiveTaskCard.jsx","tags":["dev","test","autodocs"]},"components-interactivetaskcard--review-task":{"type":"story","id":"components-interactivetaskcard--review-task","name":"Review Task","title":"Components/InteractiveTaskCard","importPath":"./src/components/InteractiveTaskCard.stories.jsx","componentPath":"./src/components/InteractiveTaskCard.jsx","tags":["dev","test","autodocs"]},"components-meeting--docs":{"id":"components-meeting--docs","title":"Components/Meeting","name":"Docs","importPath":"./src/components/Meeting.stories.jsx","type":"docs","tags":["dev","test","autodocs"],"storiesImports":[]},"components-meeting--default":{"type":"story","id":"components-meeting--default","name":"Default","title":"Components/Meeting","importPath":"./src/components/Meeting.stories.jsx","componentPath":"./src/components/Meeting.jsx","tags":["dev","test","autodocs"]},"components-milestone--docs":{"id":"components-milestone--docs","title":"Components/Milestone","name":"Docs","importPath":"./src/components/Milestone.stories.jsx","type":"docs","tags":["dev","test","autodocs"],"storiesImports":[]},"components-milestone--default":{"type":"story","id":"components-milestone--default","name":"Default","title":"Components/Milestone","importPath":"./src/components/Milestone.stories.jsx","componentPath":"./src/components/Milestone.jsx","tags":["dev","test","autodocs"]},"components-milestone--detailed":{"type":"story","id":"components-milestone--detailed","name":"Detailed","title":"Components/Milestone","importPath":"./src/components/Milestone.stories.jsx","componentPath":"./src/components/Milestone.jsx","tags":["dev","test","autodocs"]},"components-progress--docs":{"id":"components-progress--docs","title":"Components/Progress","name":"Docs","importPath":"./src/components/Progress.stories.jsx","type":"docs","tags":["dev","test","autodocs"],"storiesImports":[]},"components-progress--basic-progress":{"type":"story","id":"components-progress--basic-progress","name":"Basic Progress","title":"Components/Progress","importPath":"./src/components/Progress.stories.jsx","componentPath":"./src/components/Progress.jsx","tags":["dev","test","autodocs"]},"components-progress--milestone-progress":{"type":"story","id":"components-progress--milestone-progress","name":"Milestone Progress","title":"Components/Progress","importPath":"./src/components/Progress.stories.jsx","componentPath":"./src/components/Progress.jsx","tags":["dev","test","autodocs"]},"components-resourcecard--docs":{"id":"components-resourcecard--docs","title":"Components/ResourceCard","name":"Docs","importPath":"./src/components/ResourceCard.stories.jsx","type":"docs","tags":["dev","test","autodocs"],"storiesImports":[]},"components-resourcecard--basic-resource":{"type":"story","id":"components-resourcecard--basic-resource","name":"Basic Resource","title":"Components/ResourceCard","importPath":"./src/components/ResourceCard.stories.jsx","componentPath":"./src/components/ResourceCard.jsx","tags":["dev","test","autodocs"]},"components-resourcecard--git-hub-repository":{"type":"story","id":"components-resourcecard--git-hub-repository","name":"Git Hub Repository","title":"Components/ResourceCard","importPath":"./src/components/ResourceCard.stories.jsx","componentPath":"./src/components/ResourceCard.jsx","tags":["dev","test","autodocs"]},"components-resourcecard--video-tutorial":{"type":"story","id":"components-resourcecard--video-tutorial","name":"Video Tutorial","title":"Components/ResourceCard","importPath":"./src/components/ResourceCard.stories.jsx","componentPath":"./src/components/ResourceCard.jsx","tags":["dev","test","autodocs"]},"components-resourcecard--design-assets":{"type":"story","id":"components-resourcecard--design-assets","name":"Design Assets","title":"Components/ResourceCard","importPath":"./src/components/ResourceCard.stories.jsx","componentPath":"./src/components/ResourceCard.jsx","tags":["dev","test","autodocs"]},"components-shoutout--docs":{"id":"components-shoutout--docs","title":"Components/Shoutout","name":"Docs","importPath":"./src/components/Shoutout.stories.jsx","type":"docs","tags":["dev","test","autodocs"],"storiesImports":[]},"components-shoutout--default":{"type":"story","id":"components-shoutout--default","name":"Default","title":"Components/Shoutout","importPath":"./src/components/Shoutout.stories.jsx","componentPath":"./src/components/Shoutout.jsx","tags":["dev","test","autodocs"]},"components-shoutout--long-reason":{"type":"story","id":"components-shoutout--long-reason","name":"Long Reason","title":"Components/Shoutout","importPath":"./src/components/Shoutout.stories.jsx","componentPath":"./src/components/Shoutout.jsx","tags":["dev","test","autodocs"]},"components-standupsummary--docs":{"id":"components-standupsummary--docs","title":"Components/StandUpSummary","name":"Docs","importPath":"./src/components/StandUpSummary.stories.jsx","type":"docs","tags":["dev","test","autodocs"],"storiesImports":[]},"components-standupsummary--single-text":{"type":"story","id":"components-standupsummary--single-text","name":"Single Text","title":"Components/StandUpSummary","importPath":"./src/components/StandUpSummary.stories.jsx","componentPath":"./src/components/StandUpSummary.jsx","tags":["dev","test","autodocs"]},"components-standupsummary--list-summary":{"type":"story","id":"components-standupsummary--list-summary","name":"List Summary","title":"Components/StandUpSummary","importPath":"./src/components/StandUpSummary.stories.jsx","componentPath":"./src/components/StandUpSummary.jsx","tags":["dev","test","autodocs"]},"components-task--docs":{"id":"components-task--docs","title":"Components/Task","name":"Docs","importPath":"./src/components/Task.stories.jsx","type":"docs","tags":["dev","test","autodocs"],"storiesImports":[]},"components-task--default":{"type":"story","id":"components-task--default","name":"Default","title":"Components/Task","importPath":"./src/components/Task.stories.jsx","componentPath":"./src/components/Task.jsx","tags":["dev","test","autodocs"]},"components-task--completed":{"type":"story","id":"components-task--completed","name":"Completed","title":"Components/Task","importPath":"./src/components/Task.stories.jsx","componentPath":"./src/components/Task.jsx","tags":["dev","test","autodocs"]},"components-timeline--docs":{"id":"components-timeline--docs","title":"Components/Timeline","name":"Docs","importPath":"./src/components/Timeline.stories.jsx","type":"docs","tags":["dev","test","autodocs"],"storiesImports":[]},"components-timeline--default":{"type":"story","id":"components-timeline--default","name":"Default","title":"Components/Timeline","importPath":"./src/components/Timeline.stories.jsx","componentPath":"./src/components/Timeline.jsx","tags":["dev","test","autodocs"]},"components-timeline--multi-event":{"type":"story","id":"components-timeline--multi-event","name":"Multi Event","title":"Components/Timeline","importPath":"./src/components/Timeline.stories.jsx","componentPath":"./src/components/Timeline.jsx","tags":["dev","test","autodocs"]}}}